{
  "project_info": {
    "project_number": "556772722514",
    "project_id": "fir-jc-17409",
    "storage_bucket": "fir-jc-17409.firebasestorage.app"
  },
  "client": [
    {
      "client_info": {
        "mobilesdk_app_id": "1:556772722514:android:9c189a69575e4a20df1c8b",
        "android_client_info": {
          "package_name": "com.buildingbadd.demojc"
        }
      },
      "oauth_client": [],
      "api_key": [
        {
          "current_key": "AIzaSyA1L7cSdA9pcGoyZ2QwCg_TxzFzUDKBRO0"
        }
      ],
      "services": {
        "appinvite_service": {
          "other_platform_oauth_client": []
        }
      }
    }
  ],
  "configuration_version": "1"
}